shaq_probability/Binomialdistribution.py
shaq_probability/Gaussiandistribution.py
shaq_probability/Generaldistribution.py
shaq_probability/__init__.py
shaq_probability-0.2.dist-info/METADATA
shaq_probability-0.2.dist-info/WHEEL
shaq_probability-0.2.dist-info/top_level.txt
shaq_probability-0.2.dist-info/RECORD
