Metadata-Version: 2.1
Name: shaq-probability
Version: 0.2
Summary: Probability distributions
Home-page: UNKNOWN
Author: Mohammed Shaqura
Author-email: mohammad.shaqura@gmail.com
License: UNKNOWN
Platform: UNKNOWN
